{
  "doc_type": "lk_news",
  "doc_id": "2024-02-20-adaderanasinhalalk-45d77409",
  "num": "adaderanasinhalalk-45d77409",
  "date_str": "2024-02-20",
  "description": "UN FAO \u0d86\u0dc3\u0dd2\u0dba\u0dcf - \u0db4\u0dd0\u0dc3\u0dd2\u0dc6\u0dd2\u0d9a\u0dca \u0d9a\u0dbd\u0dcf\u0db4\u0dd3\u0dba \u0dc3\u0db8\u0dd4\u0dc5\u0dd4\u0dc0 \u0d87\u0dbb\u0db9\u0dda",
  "url_metadata": "http://sinhala.adaderana.lk/news/193608",
  "lang": "si",
  "newspaper_id": "adaderanasinhalalk",
  "time_ut": 1708406040.0
}