{
  "doc_type": "lk_news",
  "doc_id": "2025-07-21-adaderanasinhalalk-9f607786",
  "num": "adaderanasinhalalk-9f607786",
  "date_str": "2025-07-21",
  "description": "\u0dc3\u0da2\u0dd2\u0db1\u0dca \u0dc0\u0dcf\u0dc3\u0dca\u0da7 \u0d91\u0dbb\u0dd9\u0dc4\u0dd2 \u0db1\u0da9\u0dd4\u0dc0\u0d9a\u0dca \u0dba\u0dc5\u0dd2 \u0dc0\u0dd2\u0db7\u0dcf\u0d9c\u0dba\u0da7 \u0d9c\u0db1\u0dca\u0db1\u0dcf \u0dbd\u0dd9\u0dc3\u0da7 \u0db1\u0dd2\u0dba\u0ddd\u0d9c",
  "url_metadata": "http://sinhala.adaderana.lk/news/212489",
  "lang": "si",
  "newspaper_id": "adaderanasinhalalk",
  "time_ut": 1753113840.0
}