{
  "doc_type": "lk_news",
  "doc_id": "2025-10-01-virakesarilk-ab9b5106",
  "num": "virakesarilk-ab9b5106",
  "date_str": "2025-10-01",
  "description": "\u0bb2\u0bbe\u0baa\u0bcd \u0b8e\u0bb0\u0bbf\u0bb5\u0bbe\u0baf\u0bc1 \u0bb5\u0bbf\u0bb2\u0bc8 \u0ba4\u0bca\u0b9f\u0bb0\u0bcd\u0baa\u0bbf\u0bb2\u0bcd \u0bb5\u0bc6\u0bb3\u0bbf\u0baf\u0bbe\u0ba9 \u0ba4\u0b95\u0bb5\u0bb2\u0bcd!",
  "url_metadata": "https://www.virakesari.lk/article/226580",
  "lang": "ta",
  "newspaper_id": "virakesarilk",
  "time_ut": 1759308120.0
}