{
  "doc_type": "lk_news",
  "doc_id": "2024-04-02-adaderanasinhalalk-712a38a9",
  "num": "adaderanasinhalalk-712a38a9",
  "date_str": "2024-04-02",
  "description": "\u0db1\u0dd0\u0d9c\u0dd9\u0db1\u0dc4\u0dd2\u0dbb \u0dba\u0dd4\u0dbb\u0ddd\u0db4\u0dba\u0dda \u0dbb\u0dd0\u0d9a\u0dd2\u0dba\u0dcf \u0d85\u0dc0\u0dc3\u0dca\u0dae\u0dcf \u0dbd\u0dd0\u0db6\u0dd4\u0dab\u0dd4 \u0d85\u0db4\u0dda \u0d85\u0dba \u0dc0\u0dd2\u0db3\u0dd2\u0db1 \u0daf\u0dd4\u0d9a",
  "url_metadata": "http://sinhala.adaderana.lk/news/195217",
  "lang": "si",
  "newspaper_id": "adaderanasinhalalk",
  "time_ut": 1712054220.0
}