{
  "doc_type": "lk_news",
  "doc_id": "2025-11-27-adalk-daa4e4f1",
  "num": "adalk-daa4e4f1",
  "date_str": "2025-11-27",
  "description": "\u0d9c\u0db8\u0dca\u0db4\u0ddc\u0dc5 \u0db1\u0dd4\u0dc0\u0dbb\u0d91\u0dc5\u0dd2\u0dba \u0db8\u0dcf\u0dbb\u0dca\u0d9c\u0dba \u0dad\u0dcf\u0dc0\u0d9a\u0dcf\u0dbd\u0dd2\u0d9a\u0dc0 \u0dc0\u0dc3\u0dba\u0dd2",
  "url_metadata": "https://www.ada.lk/breaking_news/\u0d9c\u0db8\u0dca\u0db4\u0ddc\u0dc5-\u0db1\u0dd4\u0dc0\u0dbb\u0d91\u0dc5\u0dd2\u0dba-\u0db8\u0dcf\u0dbb\u0dca\u0d9c\u0dba-\u0dad\u0dcf\u0dc0\u0d9a\u0dcf\u0dbd\u0dd2\u0d9a\u0dc0-\u0dc0\u0dc3\u0dba\u0dd2/11-419916",
  "lang": "si",
  "newspaper_id": "adalk",
  "time_ut": 1764215914.0
}