{
  "doc_type": "lk_news",
  "doc_id": "2024-05-10-adalk-d8e126f3",
  "num": "adalk-d8e126f3",
  "date_str": "2024-05-10",
  "description": "\u0dc4\u0dbb\u0dd2\u0dad \u0db8\u0dcf\u0dc0\u0dad\u0dd9\u0db1\u0dca \u0db4\u0dd2\u0da7\u0d9a\u0dbb\u0db1\u0dca\u0db1 \u0d9c\u0dd2\u0dba \u0dbd\u0d9a\u0dca\u0dc2 130\u0d9a \u0db8\u0dad\u0dca\u0db4\u0dd0\u0db1\u0dca \u0dc4\u0dcf \u0daf\u0dd4\u0db8\u0dca\u0dc0\u0dd0\u0da7\u0dd2 \u0d85\u0dbd\u0dca\u0dbd\u0dba\u0dd2",
  "url_metadata": "https://www.ada.lk/breaking_news/\u0dc4\u0dbb\u0dd2\u0dad-\u0db8\u0dcf\u0dc0\u0dad\u0dd9\u0db1\u0dca-\u0db4\u0dd2\u0da7\u0d9a\u0dbb\u0db1\u0dca\u0db1-\u0d9c\u0dd2\u0dba-\u0dbd\u0d9a\u0dca\u0dc2-130\u0d9a-\u0db8\u0dad\u0dca\u0db4\u0dd0\u0db1\u0dca-\u0dc4\u0dcf-\u0daf\u0dd4\u0db8\u0dca\u0dc0\u0dd0\u0da7\u0dd2-\u0d85\u0dbd\u0dca\u0dbd\u0dba\u0dd2/11-409547",
  "lang": "si",
  "newspaper_id": "adalk",
  "time_ut": 1715325545.0
}