{
  "doc_type": "lk_news",
  "doc_id": "2024-05-31-virakesarilk-b19b630e",
  "num": "virakesarilk-b19b630e",
  "date_str": "2024-05-31",
  "description": "\u0ba4\u0bca\u0b9f\u0bb0\u0bcd \u0ba4\u0bbf\u0baf\u0bbe\u0ba9\u0ba4\u0bcd\u0ba4\u0bbf\u0bb2\u0bcd \u0b88\u0b9f\u0bc1\u0baa\u0b9f\u0bcd\u0b9f\u0bbf\u0bb0\u0bc1\u0b95\u0bcd\u0b95\u0bc1\u0bae\u0bcd \u0b87\u0ba8\u0bcd\u0ba4\u0bbf\u0baf \u0baa\u0bbf\u0bb0\u0ba4\u0bae\u0bb0\u0bcd \u0ba8\u0bb0\u0bc7\u0ba8\u0bcd\u0ba4\u0bbf\u0bb0 \u0bae\u0bcb\u0b9f\u0bbf",
  "url_metadata": "https://www.virakesari.lk/article/184982",
  "lang": "ta",
  "newspaper_id": "virakesarilk",
  "time_ut": 1717156020.0
}