{
  "doc_type": "lk_news",
  "doc_id": "2025-11-19-lankadeepalk-4bc16fe2",
  "num": "lankadeepalk-4bc16fe2",
  "date_str": "2025-11-19",
  "description": "\u0d8b\u0dad\u0dd4\u0dbb\u0dd4 \u0db1\u0dd0\u0d9c\u0dd9\u0db1\u0dc4\u0dd2\u0dbb \u0d9c\u0dd0\u0da7\u0dbd\u0dd4 \u0dc0\u0dbd\u0da7 \u0db1\u0dc0 \u0daf\u0dda\u0dc1\u0db4\u0dcf\u0dbd\u0db1 \u0dc0\u0dd2\u0dc3\u0db3\u0dd4\u0db8\u0d9a\u0dca",
  "url_metadata": "https://www.lankadeepa.lk/news/\u0d8b\u0dad\u0dbb-\u0db1\u0d9c\u0db1\u0dc4\u0dbb-\u0d9c\u0da7\u0dbd-\u0dc0\u0dbd\u0da7-\u0db1\u0dc0-\u0daf\u0dc1\u0db4\u0dbd\u0db1-\u0dc0\u0dc3\u0db3\u0db8\u0d9a/101-683490",
  "lang": "si",
  "newspaper_id": "lankadeepalk",
  "time_ut": 1763559160.0
}