{
  "doc_type": "lk_news",
  "doc_id": "2023-11-26-colombotelegraphcom-8846eee4",
  "num": "colombotelegraphcom-8846eee4",
  "date_str": "2023-11-26",
  "description": "President Resists Independent Review Of His Nominees To High Posts By Constitutional Council",
  "url_metadata": "https://www.colombotelegraph.com/index.php/president-resists-independent-review-of-his-nominees-to-high-posts-by-constitutional-council/",
  "lang": "en",
  "newspaper_id": "colombotelegraphcom",
  "time_ut": 1700972667.0
}