{
  "doc_type": "lk_news",
  "doc_id": "2025-11-28-lankadeepalk-4fd6c69a",
  "num": "lankadeepalk-4fd6c69a",
  "date_str": "2025-11-28",
  "description": "\u0d85\u2018\u0db4\u0dd4\u0dbb \u0db6\u0db1\u0dca\u0db0\u0db1\u0dcf\u0d9c\u0dcf\u0dbb\u0dba\u0dad\u0dca \u0dba\u0da7\u0dc0\u0dda",
  "url_metadata": "https://www.lankadeepa.lk/news/\u0d85\u0db4\u0dbb-\u0db6\u0db1\u0db0\u0db1\u0d9c\u0dbb\u0dba\u0dad-\u0dba\u0da7\u0dc0/101-684155",
  "lang": "si",
  "newspaper_id": "lankadeepalk",
  "time_ut": 1764339533.0
}