{
  "doc_type": "lk_news",
  "doc_id": "2025-11-30-lankadeepalk-af720adb",
  "num": "lankadeepalk-af720adb",
  "date_str": "2025-11-30",
  "description": "\u0d85\u0db1\u0dd2\u0dc0\u0dad\u0dca\u0dad \u0db6\u0dd2\u0d82\u0d9c\u0dba\u0da7 \u0db4\u0dc3\u0dca \u0d9c\u0dbd\u0dca \u0db4\u0dd9\u0dbb\u0dbd\u0dd9\u0dba\u0dd2",
  "url_metadata": "https://www.lankadeepa.lk/news/\u0d85\u0db1\u0dc0\u0dad\u0dad-\u0db6\u0d9c\u0dba\u0da7-\u0db4\u0dc3-\u0d9c\u0dbd-\u0db4\u0dbb\u0dbd\u0dba/101-684317",
  "lang": "si",
  "newspaper_id": "lankadeepalk",
  "time_ut": 1764499204.0
}