{
  "doc_type": "lk_news",
  "doc_id": "2024-03-17-adalk-369a4bf5",
  "num": "adalk-369a4bf5",
  "date_str": "2024-03-17",
  "description": "\u0da2\u0dd3\u0dc0\u0db1 \u0dc3\u0dc4\u0dad\u0dd2\u0d9a\u0dba \u0db1\u0ddc\u0daf\u0dd4\u0db1\u0dca\u0db1\u0ddc\u0dad\u0dca \u0dc3\u0dcf\u0db8 \u0dc0\u0dd2\u0db1\u0dd2\u0dc3\u0dd4\u0dbb\u0dd4 \u0db4\u0daf\u0dc0\u0dd2\u0dba \u0d85\u0dc4\u0ddd\u0dc3\u0dd2\u0dba\u0dd2",
  "url_metadata": "https://www.ada.lk/breaking_news/\u0da2\u0dd3\u0dc0\u0db1-\u0dc3\u0dc4\u0dad\u0dd2\u0d9a\u0dba-\u0db1\u0ddc\u0daf\u0dd4\u0db1\u0dca\u0db1\u0ddc\u0dad\u0dca-\u0dc3\u0dcf\u0db8-\u0dc0\u0dd2\u0db1\u0dd2\u0dc3\u0dd4\u0dbb\u0dd4-\u0db4\u0daf\u0dc0\u0dd2\u0dba-\u0d85\u0dc4\u0ddd\u0dc3\u0dd2\u0dba\u0dd2/11-408642",
  "lang": "si",
  "newspaper_id": "adalk",
  "time_ut": 1710642868.0
}