{
  "doc_type": "lk_news",
  "doc_id": "2024-05-20-adalk-479cd2be",
  "num": "adalk-479cd2be",
  "date_str": "2024-05-20",
  "description": "\u0d89\u0dbb\u0dcf\u0db1 \u0da2\u0db1\u0db4\u0dad\u0dd2 \u0d9c\u0db8\u0db1\u0dca \u0d9c\u0dad\u0dca \u0dc4\u0dd9\u0dbd\u0dd2\u0d9a\u0ddc\u0db4\u0dca\u0da7\u0dbb\u0dca \u0dba\u0dcf\u0db1\u0dba\u0dda \u0dc3\u0dd4\u0db1\u0dca\u0db6\u0dd4\u0db1\u0dca \u0dc4\u0db8\u0dd4\u0dc0\u0dd9\u0dba\u0dd2",
  "url_metadata": "https://www.ada.lk/breaking_news/\u0d89\u0dbb\u0dcf\u0db1-\u0da2\u0db1\u0db4\u0dad\u0dd2-\u0d9c\u0db8\u0db1\u0dca-\u0d9c\u0dad\u0dca-\u0dc4\u0dd9\u0dbd\u0dd2\u0d9a\u0ddc\u0db4\u0dca\u0da7\u0dbb\u0dca-\u0dba\u0dcf\u0db1\u0dba\u0dda-\u0dc3\u0dd4\u0db1\u0dca\u0db6\u0dd4\u0db1\u0dca-\u0dc4\u0db8\u0dd4\u0dc0\u0dd9\u0dba\u0dd2/11-409728",
  "lang": "si",
  "newspaper_id": "adalk",
  "time_ut": 1716172770.0
}