{
  "doc_type": "lk_news",
  "doc_id": "2025-12-05-lankadeepalk-0802838f",
  "num": "lankadeepalk-0802838f",
  "date_str": "2025-12-05",
  "description": "\u0dc0\u0dcf\u0dbb\u0dd2\u0db8\u0dcf\u0dbb\u0dca\u0d9c \u0d87\u0db8\u0dad\u0dd2\u0da7 \u0da2\u0db8\u0dca\u0db4\u0dbb \u0d85\u0db3\u0dd2\u0db1\u0dca\u0db1 \u0dc0\u0dd9\u0db1\u0dc0\u0dcf",
  "url_metadata": "https://www.lankadeepa.lk/news/\u0dc0\u0dbb\u0db8\u0dbb\u0d9c-\u0d87\u0db8\u0dad\u0da7-\u0da2\u0db8\u0db4\u0dbb-\u0d85\u0db3\u0db1\u0db1-\u0dc0\u0db1\u0dc0/101-684745",
  "lang": "si",
  "newspaper_id": "lankadeepalk",
  "time_ut": 1764938222.0
}