{
  "doc_type": "lk_news",
  "doc_id": "2025-12-10-tamilmirrorlk-8dd5a72b",
  "num": "tamilmirrorlk-8dd5a72b",
  "date_str": "2025-12-10",
  "description": "\u0ba4\u0ba8\u0bcd\u0ba4\u0bc8 \u0b8e\u0b9a\u0bcd\u0b9a\u0bb0\u0bbf\u0ba4\u0bcd\u0ba4\u0ba4\u0bbe\u0bb2\u0bcd \u0b89\u0baf\u0bbf\u0bb0\u0bc8 \u0bae\u0bbe\u0baf\u0bcd\u0ba4\u0bcd\u0ba4 \u0b9a\u0bbf\u0bb1\u0bc1\u0bae\u0bbf",
  "url_metadata": "https://www.tamilmirror.lk/\u0bae\u0bb2\u0bc8\u0baf\u0b95\u0bae\u0bcd/\u0ba4\u0ba8\u0bcd\u0ba4\u0bc8-\u0b8e\u0b9a\u0bcd\u0b9a\u0bb0\u0bbf\u0ba4\u0bcd\u0ba4\u0ba4\u0bbe\u0bb2\u0bcd-\u0b89\u0baf\u0bbf\u0bb0\u0bc8-\u0bae\u0bbe\u0baf\u0bcd\u0ba4\u0bcd\u0ba4-\u0b9a\u0bbf\u0bb1\u0bc1\u0bae\u0bbf/76-369360",
  "lang": "ta",
  "newspaper_id": "tamilmirrorlk",
  "time_ut": 1765346576.0
}