{
  "doc_type": "lk_news",
  "doc_id": "2025-11-23-lankadeepalk-cc8fea94",
  "num": "lankadeepalk-cc8fea94",
  "date_str": "2025-11-23",
  "description": "\u0da2\u0dd3\u0dc0\u0db1\u0dca - \u0dc3\u0dd3\u0dad\u0dd9\u0dba\u0dd2 \u0d85\u0dad\u0dd2\u0db1\u0dad \u0d9c\u0db1\u0dd2\u0dad\u0dd2",
  "url_metadata": "https://www.lankadeepa.lk/news/\u0da2\u0dc0\u0db1-\u0dc3\u0dad\u0dba-\u0d85\u0dad\u0db1\u0dad-\u0d9c\u0db1\u0dad/101-683672",
  "lang": "si",
  "newspaper_id": "lankadeepalk",
  "time_ut": 1763881793.0
}