{
  "doc_type": "lk_news",
  "doc_id": "2025-08-25-islandlk-14101fb8",
  "num": "islandlk-14101fb8",
  "date_str": "2025-08-25",
  "description": "Seylan Bank becomes the first Sri Lankan bank to achieve ISO 22301 certification for Business Continuity with an extended scope",
  "url_metadata": "http://island.lk/seylan-bank-becomes-the-first-sri-lankan-bank-to-achieve-iso-22301-certification-for-business-continuity-with-an-extended-scope/",
  "lang": "en",
  "newspaper_id": "islandlk",
  "time_ut": 1756145940.0
}