{
  "doc_type": "lk_news",
  "doc_id": "2024-08-12-virakesarilk-72bcfd6d",
  "num": "virakesarilk-72bcfd6d",
  "date_str": "2024-08-12",
  "description": "\u0b85\u0bb0\u0b9a\u0bbe\u0b99\u0bcd\u0b95 \u0b85\u0b9a\u0bcd\u0b9a\u0b95\u0ba4\u0bcd\u0ba4\u0bbf\u0bb1\u0bcd\u0b95\u0bc1 \u0baa\u0bb2\u0ba4\u0bcd\u0ba4 \u0baa\u0bbe\u0ba4\u0bc1\u0b95\u0bbe\u0baa\u0bcd\u0baa\u0bc1",
  "url_metadata": "https://www.virakesari.lk/article/190913",
  "lang": "ta",
  "newspaper_id": "virakesarilk",
  "time_ut": 1723464360.0
}