{
  "doc_type": "lk_news",
  "doc_id": "2025-11-23-lankadeepalk-527d394a",
  "num": "lankadeepalk-527d394a",
  "date_str": "2025-11-23",
  "description": "\u0d9c\u0dcf\u0dbd\u0dd4\u0db8\u0dd4\u0dc0\u0daf\u0ddc\u0dbb \u0da9\u0dca\u200d\u0dbb\u0ddd\u0db1 \u0dba\u0dd0\u0dc0\u0dd4 \u0dad\u0dbb\u0dd4\u0dab\u0dba\u0dd9\u0d9a\u0dca \u0db8\u0dcf\u0da7\u0dca\u0da7\u0dd4",
  "url_metadata": "https://www.lankadeepa.lk/news/\u0d9c\u0dbd\u0db8\u0dc0\u0daf\u0dbb-\u0da9\u0dbb\u0db1-\u0dba\u0dc0-\u0dad\u0dbb\u0dab\u0dba\u0d9a-\u0db8\u0da7\u0da7/101-683701",
  "lang": "si",
  "newspaper_id": "lankadeepalk",
  "time_ut": 1763916210.0
}