{
  "doc_type": "lk_news",
  "doc_id": "2025-11-17-adalk-8d9686c0",
  "num": "adalk-8d9686c0",
  "date_str": "2025-11-17",
  "description": "\u0db8\u0dd3\u0da7\u0dd2\u0dba\u0dcf\u0d9c\u0ddc\u0da9 \u0dc0\u0dd9\u0da9\u0dd2 \u0dad\u0dd0\u0db6\u0dd2\u0db8\u0d9a\u0dd2\u0db1\u0dca \u0d9a\u0dcf\u0db1\u0dca\u0dad\u0dcf\u0dc0\u0d9a\u0dca \u0db8\u0dbb\u0dd4\u0da7",
  "url_metadata": "https://www.ada.lk/breaking_news/\u0db8\u0dd3\u0da7\u0dd2\u0dba\u0dcf\u0d9c\u0ddc\u0da9-\u0dc0\u0dd9\u0da9\u0dd2-\u0dad\u0dd0\u0db6\u0dd2\u0db8\u0d9a\u0dd2\u0db1\u0dca-\u0d9a\u0dcf\u0db1\u0dca\u0dad\u0dcf\u0dc0\u0d9a\u0dca-\u0db8\u0dbb\u0dd4\u0da7/11-419732",
  "lang": "si",
  "newspaper_id": "adalk",
  "time_ut": 1763395485.0
}