{
  "doc_type": "lk_news",
  "doc_id": "2025-11-20-adalk-ed374c7d",
  "num": "adalk-ed374c7d",
  "date_str": "2025-11-20",
  "description": "\u0db8\u0dad\u0dca\u0daf\u0dca\u200d\u0dbb\u0dc0\u0dca\u200d\u0dba \u0dc3\u0db8\u0d9c \u0d85\u0dad\u0dca\u0d85\u0da9\u0d82\u0d9c\u0dd4\u0dc0\u0da7 \u0d9c\u0dad\u0dca \u0dba\u0dcf\u0dad\u0dca\u200d\u0dbb\u0dcf\u0dc0 \u0dad\u0d82\u0d9c\u0dbd\u0dca\u0dbd \u0dc0\u0dbb\u0dcf\u0dba\u0da7 \u0d9c\u0dd9\u0db1\u0dd9\u0dba\u0dd2",
  "url_metadata": "https://www.ada.lk/breaking_news/\u0db8\u0dad\u0dca\u0daf\u0dca\u200d\u0dbb\u0dc0\u0dca\u200d\u0dba-\u0dc3\u0db8\u0d9c-\u0d85\u0dad\u0dca\u0d85\u0da9\u0d82\u0d9c\u0dd4\u0dc0\u0da7-\u0d9c\u0dad\u0dca-\u0dba\u0dcf\u0dad\u0dca\u200d\u0dbb\u0dcf\u0dc0-\u0dad\u0d82\u0d9c\u0dbd\u0dca\u0dbd-\u0dc0\u0dbb\u0dcf\u0dba\u0da7-\u0d9c\u0dd9\u0db1\u0dd9\u0dba\u0dd2/11-419790",
  "lang": "si",
  "newspaper_id": "adalk",
  "time_ut": 1763654727.0
}