{
  "doc_type": "lk_news",
  "doc_id": "2024-01-20-adaderanalk-1c54f817",
  "num": "adaderanalk-1c54f817",
  "date_str": "2024-01-20",
  "description": "\u2018Look Africa\u2019 initiative marks commencement of new economic journey between Sri Lanka and Africa \u2013 Minister",
  "url_metadata": "https://www.adaderana.lk/news/96582/look-africa-initiative-marks-commencement-of-new-economic-journey-between-sri-lanka-and-africa-minister-",
  "lang": "en",
  "newspaper_id": "adaderanalk",
  "time_ut": 1705767540.0
}