{
  "doc_type": "lk_news",
  "doc_id": "2025-10-14-colombotelegraphcom-233022a3",
  "num": "colombotelegraphcom-233022a3",
  "date_str": "2025-10-14",
  "description": "One Year Of NPP Governance: Silence On Tamil Aspirations & Uncertainty Over Provincial Council Elections",
  "url_metadata": "https://www.colombotelegraph.com/index.php/one-year-of-npp-governance-silence-on-tamil-aspirations-uncertainty-over-provincial-council-elections/",
  "lang": "en",
  "newspaper_id": "colombotelegraphcom",
  "time_ut": 1760419872.0
}