{
  "doc_type": "lk_news",
  "doc_id": "2025-11-30-dbsjeyarajcom-1fe01c57",
  "num": "dbsjeyarajcom-1fe01c57",
  "date_str": "2025-11-30",
  "description": "President  Dissanayale Declares Emergency as Devastation Caused by Cyclone Ditwa Unfolds,59 dead,203 missing. Over 800,000 People Affected with More than 100,000 Accommodated in  State -run Safety Centres,",
  "url_metadata": "https://dbsjeyaraj.com/dbsj/?p=86710",
  "lang": "en",
  "newspaper_id": "dbsjeyarajcom",
  "time_ut": 1764442320.0
}