{
  "doc_type": "lk_news",
  "doc_id": "2024-05-11-adalk-72f00ad3",
  "num": "adalk-72f00ad3",
  "date_str": "2024-05-11",
  "description": "\u0db8\u0d82\u0d9c\u0dbd \u0d9c\u0dd9\u0daf\u0dbb \u0d85\u0dc0\u0db8\u0d82\u0d9c\u0dbd\u0dca\u200d\u0dba\u0dba\u0d9a\u0dca \u0dc0\u0dd9\u0dba\u0dd2",
  "url_metadata": "https://www.ada.lk/breaking_news/\u0db8\u0d82\u0d9c\u0dbd-\u0d9c\u0dd9\u0daf\u0dbb-\u0d85\u0dc0\u0db8\u0d82\u0d9c\u0dbd\u0dca\u200d\u0dba\u0dba\u0d9a\u0dca-\u0dc0\u0dd9\u0dba\u0dd2/11-409557",
  "lang": "si",
  "newspaper_id": "adalk",
  "time_ut": 1715403757.0
}