{
  "doc_type": "lk_news",
  "doc_id": "2025-12-10-adalk-42cb13b2",
  "num": "adalk-42cb13b2",
  "date_str": "2025-12-10",
  "description": "\u0d85\u0daf \u0dc3\u0dc0\u0dc3 \u0dc4\u0dcf \u0dc4\u0dd9\u0da7 \u0d8b\u0daf\u0dda \u0db4\u0dca\u200d\u0dbb\u0db0\u0dcf\u0db1 \u0db8\u0dcf\u0dbb\u0dca\u0d9c\u0dba\u0dda \u0daf\u0dd4\u0db8\u0dca\u0dbb\u0dd2\u0dba \u0db0\u0dcf\u0dc0\u0db1\u0dba \u0dc0\u0dd9\u0db1\u0dca\u0db1\u0dda \u0db8\u0dd9\u0dc4\u0dd9\u0db8\u0dba\u0dd2",
  "url_metadata": "https://www.ada.lk/breaking_news/\u0d85\u0daf-\u0dc3\u0dc0\u0dc3-\u0dc4\u0dcf-\u0dc4\u0dd9\u0da7-\u0d8b\u0daf\u0dda-\u0db4\u0dca\u200d\u0dbb\u0db0\u0dcf\u0db1-\u0db8\u0dcf\u0dbb\u0dca\u0d9c\u0dba\u0dda-\u0daf\u0dd4\u0db8\u0dca\u0dbb\u0dd2\u0dba-\u0db0\u0dcf\u0dc0\u0db1\u0dba-\u0dc0\u0dd9\u0db1\u0dca\u0db1\u0dda-\u0db8\u0dd9\u0dc4\u0dd9\u0db8\u0dba\u0dd2/11-420168",
  "lang": "si",
  "newspaper_id": "adalk",
  "time_ut": 1765366746.0
}