{
  "doc_type": "lk_news",
  "doc_id": "2024-07-29-adalk-d9b757d7",
  "num": "adalk-d9b757d7",
  "date_str": "2024-07-29",
  "description": "\u0dab\u0dd4\u0dc0\u0db1\u0dca \u0db6\u0ddd\u0db4\u0d9c\u0dda \u0da2\u0db1\u0db4\u0dad\u0dd2 \u0dc3\u0da7\u0db1\u0da7",
  "url_metadata": "https://www.ada.lk/breaking_news/\u0dab\u0dd4\u0dc0\u0db1\u0dca-\u0db6\u0ddd\u0db4\u0d9c\u0dda-\u0da2\u0db1\u0db4\u0dad\u0dd2-\u0dc3\u0da7\u0db1\u0da7/11-411078",
  "lang": "si",
  "newspaper_id": "adalk",
  "time_ut": 1722258527.0
}