{
  "doc_type": "lk_news",
  "doc_id": "2025-07-18-virakesarilk-a828904c",
  "num": "virakesarilk-a828904c",
  "date_str": "2025-07-18",
  "description": "\u0bb2\u0bcb\u0b95\u0bc7\u0bb7\u0bcd \u0b95\u0ba9\u0b95\u0bb0\u0bbe\u0b9c\u0bcd \u0ba4\u0baf\u0bbe\u0bb0\u0bbf\u0b95\u0bcd\u0b95\u0bc1\u0bae\u0bcd '\u0bae\u0bbf\u0bb8\u0bcd\u0b9f\u0bb0\u0bcd \u0baa\u0bbe\u0bb0\u0ba4\u0bcd' \u0baa\u0b9f\u0ba4\u0bcd\u0ba4\u0bbf\u0ba9\u0bcd \u0baa\u0b9f\u0baa\u0bcd\u0baa\u0bbf\u0b9f\u0bbf\u0baa\u0bcd\u0baa\u0bc1 \u0ba8\u0bbf\u0bb1\u0bc8\u0bb5\u0bc1",
  "url_metadata": "https://www.virakesari.lk/article/220341",
  "lang": "ta",
  "newspaper_id": "virakesarilk",
  "time_ut": 1752840780.0
}