{
  "doc_type": "lk_news",
  "doc_id": "2025-11-17-lankadeepalk-f520b9b1",
  "num": "lankadeepalk-f520b9b1",
  "date_str": "2025-11-17",
  "description": "\u0db4\u0ddc\u0dbd\u0dca\u0d9c\u0dc4\u0dc0\u0dd9\u0dc5 \u0d85\u0dba\u0dc0\u0dd0\u0dba \u0dc3\u0db8\u0dca\u0db8\u0dad\u0dba\u0dd2",
  "url_metadata": "https://www.lankadeepa.lk/news/\u0db4\u0dbd\u0d9c\u0dc4\u0dc0\u0dc5-\u0d85\u0dba\u0dc0\u0dba-\u0dc3\u0db8\u0db8\u0dad\u0dba/101-683301",
  "lang": "si",
  "newspaper_id": "lankadeepalk",
  "time_ut": 1763373475.0
}