{
  "doc_class_label": "lk_news",
  "doc_class_emoji": "\ud83d\udcc4",
  "doc_class_description": "A collection of lk_news documents.",
  "time_updated": "2025-10-26 00:19:09",
  "n_docs": 82937,
  "n_docs_with_pdfs": 0,
  "n_docs_with_text": 82937,
  "n_docs_with_excel": 0,
  "n_docs_with_tabular": 0,
  "date_str_min": "2021-09-12",
  "date_str_max": "2025-10-25",
  "dataset_size": 1225383114,
  "url_source_list": [
    "https://www.virakesari.lk",
    "http://sinhala.adaderana.lk",
    "https://www.tamilmirror.lk",
    "https://www.adaderana.lk",
    "https://www.ada.lk",
    "https://www.ft.lk",
    "http://island.lk",
    "https://economynext.com",
    "https://www.dailymirror.lk",
    "https://www.lankadeepa.lk",
    "https://www.colombotelegraph.com",
    "https://www.bbc.com",
    "https://dbsjeyaraj.com",
    "https://www.newsfirst.lk",
    "https://english.newsfirst.lk"
  ],
  "url_data": "https://github.com/nuuuwan/lk_news/tree/data/data/lk_news",
  "url_chart": "https://raw.githubusercontent.com/nuuuwan/lk_news/refs/heads/data/data/lk_news/docs_by_month_and_lang.png",
  "langs": [
    "en",
    "si",
    "ta"
  ],
  "latest_doc_d": {
    "doc_type": "lk_news",
    "doc_id": "2025-10-25-lankadeepalk-18a06b6b",
    "num": "lankadeepalk-18a06b6b",
    "date_str": "2025-10-25",
    "description": "\u0dbb\u0dad\u0db9\u0dbd\u0dcf \u0d94\u0dba \u0db4\u0dd2\u0da7\u0dcf\u0dbb \u0d9c\u0dbd\u0dcf \u0d9c\u0ddc\u0dba\u0db8 \u0dc0\u0dd2\u0db1\u0dcf\u0dc1 \u0dc0\u0dd9\u0dbd\u0dcf",
    "url_metadata": "https://www.lankadeepa.lk/news/\u0dbb\u0dad\u0db9\u0dbd-\u0d94\u0dba-\u0db4\u0da7\u0dbb-\u0d9c\u0dbd-\u0d9c\u0dba\u0db8-\u0dc0\u0db1\u0dc1-\u0dc0\u0dbd/101-682045",
    "lang": "si",
    "newspaper_id": "lankadeepalk",
    "time_ut": 1761416923.0
  }
}