{
  "doc_type": "lk_news",
  "doc_id": "2025-10-02-adalk-ee313a7b",
  "num": "adalk-ee313a7b",
  "date_str": "2025-10-02",
  "description": "\u0db1\u0dd9\u0dc0\u0dd2\u0dbd\u0dca \u0dbd\u0db6\u0db1 17 \u0daf\u0d9a\u0dca\u0dc0\u0dcf \u0dbb\u0d9a\u0dca\u0dc2\u0dd2\u0dad \u0db6\u0db1\u0dca\u0db0\u0db1\u0dcf\u0d9c\u0dcf\u0dbb \u0d9c\u0dad \u0d9a\u0dd2\u0dbb\u0dd3\u0db8\u0da7 \u0db1\u0dd2\u0dba\u0ddd\u0d9c",
  "url_metadata": "https://www.ada.lk/breaking_news/\u0db1\u0dd9\u0dc0\u0dd2\u0dbd\u0dca-\u0dbd\u0db6\u0db1-17-\u0daf\u0d9a\u0dca\u0dc0\u0dcf-\u0dbb\u0d9a\u0dca\u0dc2\u0dd2\u0dad-\u0db6\u0db1\u0dca\u0db0\u0db1\u0dcf\u0d9c\u0dcf\u0dbb-\u0d9c\u0dad-\u0d9a\u0dd2\u0dbb\u0dd3\u0db8\u0da7-\u0db1\u0dd2\u0dba\u0ddd\u0d9c/11-418879",
  "lang": "si",
  "newspaper_id": "adalk",
  "time_ut": 1759405172.0
}