{
  "doc_type": "lk_news",
  "doc_id": "2025-11-03-adalk-d74da0f2",
  "num": "adalk-d74da0f2",
  "date_str": "2025-11-03",
  "description": "\u0d9a\u0dcf\u0db1\u0dca\u0dad\u0dcf \u0d91\u0d9a\u0dca\u0daf\u0dd2\u0db1 \u0d9a\u0dca\u200d\u0dbb\u0dd2\u0d9a\u0da7\u0dca \u0dbd\u0ddd\u0d9a \u0d9a\u0dd4\u0dc3\u0dbd\u0dcf\u0db1\u0dba \u0d89\u0db1\u0dca\u0daf\u0dd2\u0dba\u0dcf\u0dc0\u0da7",
  "url_metadata": "https://www.ada.lk/sports/\u0d9a\u0dcf\u0db1\u0dca\u0dad\u0dcf-\u0d91\u0d9a\u0dca\u0daf\u0dd2\u0db1-\u0d9a\u0dca\u200d\u0dbb\u0dd2\u0d9a\u0da7\u0dca-\u0dbd\u0ddd\u0d9a-\u0d9a\u0dd4\u0dc3\u0dbd\u0dcf\u0db1\u0dba-\u0d89\u0db1\u0dca\u0daf\u0dd2\u0dba\u0dcf\u0dc0\u0da7/9-419464",
  "lang": "si",
  "newspaper_id": "adalk",
  "time_ut": 1762136960.0
}