{
  "doc_type": "lk_news",
  "doc_id": "2023-08-08-adalk-85209083",
  "num": "adalk-85209083",
  "date_str": "2023-08-08",
  "description": "\u0d9a\u0dd8\u0dad\u0dca\u200d\u0dbb\u0dd3\u0db8 \u0db6\u0dd4\u0daf\u0dca\u0db0\u0dd2 \u0dc0\u0dd2\u0dc2\u0dba \u0db4\u0dcf\u0dc3\u0dbd\u0dca \u0d85\u0db0\u0dca\u200d\u0dba\u0dcf\u0db4\u0db1\u0dba\u0da7 6-9 \u0dc3\u0dc4 10 - 13 \u0dc0\u0dc1\u0dba\u0dd9\u0db1\u0dca \u0d85\u0dc0\u0dc3\u0dca\u0dae\u0dcf \u0daf\u0dd9\u0d9a\u0d9a\u0daf\u0dd3",
  "url_metadata": "https://www.ada.lk/technology/\u0d9a\u0dd8\u0dad\u0dca\u200d\u0dbb\u0dd3\u0db8-\u0db6\u0dd4\u0daf\u0dca\u0db0\u0dd2-\u0dc0\u0dd2\u0dc2\u0dba-\u0db4\u0dcf\u0dc3\u0dbd\u0dca-\u0d85\u0db0\u0dca\u200d\u0dba\u0dcf\u0db4\u0db1\u0dba\u0da7-6-9-\u0dc3\u0dc4-10---13-\u0dc0\u0dc1\u0dba\u0dd9\u0db1\u0dca-\u0d85\u0dc0\u0dc3\u0dca\u0dae\u0dcf-\u0daf\u0dd9\u0d9a\u0d9a\u0daf\u0dd3/5-405108",
  "lang": "si",
  "newspaper_id": "adalk",
  "time_ut": 1691495541.0
}