{
  "doc_type": "lk_news",
  "doc_id": "2025-11-25-lankadeepalk-e91620d0",
  "num": "lankadeepalk-e91620d0",
  "date_str": "2025-11-25",
  "description": "\u0d89\u0daf\u0dd2\u0dbb\u0dd2 \u0daf\u0dd2\u0db1\u0dc0\u0dbd \u0dc0\u0dd0\u0dc3\u0dca \u0dc0\u0dd0\u0da9\u0dd2 \u0dc0\u0db1 \u0dc4\u0dd0\u0da9",
  "url_metadata": "https://www.lankadeepa.lk/latest_news/\u0d89\u0daf\u0dbb-\u0daf\u0db1\u0dc0\u0dbd-\u0dc0\u0dc3-\u0dc0\u0da9-\u0dc0\u0db1-\u0dc4\u0da9/1-683869",
  "lang": "si",
  "newspaper_id": "lankadeepalk",
  "time_ut": 1764074052.0
}