{
  "doc_type": "lk_news",
  "doc_id": "2025-10-28-adalk-9a24761e",
  "num": "adalk-9a24761e",
  "date_str": "2025-10-28",
  "description": "\u0d9a\u0dad\u0dbb\u0d9c\u0db8 \u0daf\u0dda\u0dc0\u0dcf\u0dbd\u0dba\u0dda \u0d89\u0dbd\u0dca \u0db8\u0d82\u0d9c\u0dbd\u0dca\u200d\u0dba \u0daf\u0dd9\u0dc3\u0dd0. 04 \u0daf\u0dcf \u0d87\u0dbb\u0db9\u0dd9\u0dba\u0dd2",
  "url_metadata": "https://www.ada.lk/breaking_news/\u0d9a\u0dad\u0dbb\u0d9c\u0db8-\u0daf\u0dda\u0dc0\u0dcf\u0dbd\u0dba\u0dda-\u0d89\u0dbd\u0dca-\u0db8\u0d82\u0d9c\u0dbd\u0dca\u200d\u0dba-\u0daf\u0dd9\u0dc3\u0dd0--04-\u0daf\u0dcf-\u0d87\u0dbb\u0db9\u0dd9\u0dba\u0dd2/11-419366",
  "lang": "si",
  "newspaper_id": "adalk",
  "time_ut": 1761638563.0
}