{
  "doc_type": "lk_news",
  "doc_id": "2024-04-29-adalk-21426fb1",
  "num": "adalk-21426fb1",
  "date_str": "2024-04-29",
  "description": "\u0d85\u0daf  \u0d9a\u0dcf\u0dbd\u0d9c\u0dd4\u0dab\u0dba \u0db8\u0ddc\u0d9a\u0daf \u0dc0\u0dd9\u0db1\u0dca\u0db1\u0dda",
  "url_metadata": "https://www.ada.lk/breaking_news/\u0d85\u0daf--\u0d9a\u0dcf\u0dbd\u0d9c\u0dd4\u0dab\u0dba-\u0db8\u0ddc\u0d9a\u0daf-\u0dc0\u0dd9\u0db1\u0dca\u0db1\u0dda/11-409317",
  "lang": "si",
  "newspaper_id": "adalk",
  "time_ut": 1714366077.0
}