{
  "doc_type": "lk_news",
  "doc_id": "2024-07-28-adaderanasinhalalk-e68edf46",
  "num": "adaderanasinhalalk-e68edf46",
  "date_str": "2024-07-28",
  "description": "\u0d9a\u0dcf\u0db1\u0dca\u0dad\u0dcf \u0d86\u0dc3\u0dd2\u0dba\u0dcf\u0db1\u0dd4 \u0d9a\u0dd4\u0dc3\u0dbd\u0dcf\u0db1\u0dba\u0dda \u0d85\u0dc0\u0dc3\u0db1\u0dca \u0dad\u0dbb\u0d9c\u0dba \u0d85\u0daf",
  "url_metadata": "http://sinhala.adaderana.lk/news/199290",
  "lang": "si",
  "newspaper_id": "adaderanasinhalalk",
  "time_ut": 1722141480.0
}