{
  "doc_type": "lk_news",
  "doc_id": "2025-11-03-lankadeepalk-3c63ea35",
  "num": "lankadeepalk-3c63ea35",
  "date_str": "2025-11-03",
  "description": "\u0d89\u0dbb \u0db4\u0dd0\u0db1\u0dca\u0db1 \u0d89\u0db1\u0dca\u0daf\u0dd3\u0dba \u0db0\u0dd3\u0dc0\u0dbb\u0dba\u0db1\u0dca 35\u0d9a\u0dca \u0d85\u0dbd\u0dca\u0dbd\u0dba\u0dd2",
  "url_metadata": "https://www.lankadeepa.lk/latest_news/\u0d89\u0dbb-\u0db4\u0db1\u0db1-\u0d89\u0db1\u0daf\u0dba-\u0db0\u0dc0\u0dbb\u0dba\u0db1-35\u0d9a-\u0d85\u0dbd\u0dbd\u0dba/1-682621",
  "lang": "si",
  "newspaper_id": "lankadeepalk",
  "time_ut": 1762185794.0
}