{
  "doc_type": "lk_news",
  "doc_id": "2025-10-13-adalk-e3e8b250",
  "num": "adalk-e3e8b250",
  "date_str": "2025-10-13",
  "description": "\u0daf\u0dd2\u0dba\u0dd4\u0dab\u0dd4\u0dc0\u0da7 \u0dc4\u0ddc\u0db3\u0db8 \u0db8\u0d9f \u0d89\u0dad\u0dd2\u0dbb\u0dd2 \u0d9a\u0dd2\u0dbb\u0dd3\u0db8 \u0db1\u0ddc\u0dc0 \u0d86\u0dba\u0ddd\u0da2\u0db1\u0dba\u0dba\u0dd2",
  "url_metadata": "https://www.ada.lk/business/\u0daf\u0dd2\u0dba\u0dd4\u0dab\u0dd4\u0dc0\u0da7-\u0dc4\u0ddc\u0db3\u0db8-\u0db8\u0d9f-\u0d89\u0dad\u0dd2\u0dbb\u0dd2-\u0d9a\u0dd2\u0dbb\u0dd3\u0db8-\u0db1\u0ddc\u0dc0-\u0d86\u0dba\u0ddd\u0da2\u0db1\u0dba\u0dba\u0dd2/7-419058",
  "lang": "si",
  "newspaper_id": "adalk",
  "time_ut": 1760342688.0
}