{
  "doc_type": "lk_news",
  "doc_id": "2025-11-02-tamilmirrorlk-651d9a73",
  "num": "tamilmirrorlk-651d9a73",
  "date_str": "2025-11-02",
  "description": "300 \u0ba4\u0bbe\u0ba4\u0bcd\u0ba4\u0bbe\u0b95\u0bcd\u0b95\u0bb3\u0bc8 \u0bb5\u0bc7\u0b9f\u0bcd\u0b9f\u0bc8\u0baf\u0bbe\u0b9f\u0bbf \u0baa\u0bc6\u0ba3\u0bcd: 300+ Bedroom Videos",
  "url_metadata": "https://www.tamilmirror.lk/\u0b9a\u0bc6\u0baf\u0bcd\u0ba4\u0bbf\u0b95\u0bb3\u0bcd/300-\u0ba4\u0bbe\u0ba4\u0bcd\u0ba4\u0bbe\u0b95\u0bcd\u0b95\u0bb3\u0bc8-\u0bb5\u0bc7\u0b9f\u0bcd\u0b9f\u0bc8\u0baf\u0bbe\u0b9f\u0bbf-\u0baa\u0bc6\u0ba3\u0bcd-300-Bedroom-Videos/175-367214",
  "lang": "ta",
  "newspaper_id": "tamilmirrorlk",
  "time_ut": 1762069149.0
}