{
  "doc_type": "lk_news",
  "doc_id": "2025-11-19-lankadeepalk-56a897f9",
  "num": "lankadeepalk-56a897f9",
  "date_str": "2025-11-19",
  "description": "\u0d9a\u0dad\u0dcf\u0db1\u0dcf\u0dba\u0d9a \u0d9a\u0db1\u0dca\u0dad\u0ddd\u0dbb\u0dd4\u0dc0\u0da7 \u0db1\u0dba\u0dd9\u0d9a\u0dca \u0d87\u0dc0\u0dd2\u0dad\u0dca \u0d9a\u0dbd\u0db6\u0dbd\u0dba\u0d9a\u0dca",
  "url_metadata": "https://www.lankadeepa.lk/news/\u0d9a\u0dad\u0db1\u0dba\u0d9a-\u0d9a\u0db1\u0dad\u0dbb\u0dc0\u0da7-\u0db1\u0dba\u0d9a-\u0d87\u0dc0\u0dad-\u0d9a\u0dbd\u0db6\u0dbd\u0dba\u0d9a/101-683418",
  "lang": "si",
  "newspaper_id": "lankadeepalk",
  "time_ut": 1763530840.0
}