{
  "doc_type": "lk_news",
  "doc_id": "2025-12-06-lankadeepalk-f4545f49",
  "num": "lankadeepalk-f4545f49",
  "date_str": "2025-12-06",
  "description": "\u0d86\u0db4\u0daf\u0dcf \u0dc0\u0d9c\u0dcf \u0dc0\u0db1\u0dca\u0daf\u0dd2  \u0daf\u0dd9\u0dc3\u0dd0\u0db8\u0dca\u0db6\u0dbb\u0dca 30\u0da7 \u0d9a\u0dbd\u0dd2\u0db1\u0dca",
  "url_metadata": "https://www.lankadeepa.lk/news/\u0d86\u0db4\u0daf-\u0dc0\u0d9c-\u0dc0\u0db1\u0daf-\u0daf\u0dc3\u0db8\u0db6\u0dbb-30\u0da7-\u0d9a\u0dbd\u0db1/101-684772",
  "lang": "si",
  "newspaper_id": "lankadeepalk",
  "time_ut": 1765032409.0
}