{
  "doc_type": "lk_news",
  "doc_id": "2025-11-06-lankadeepalk-49ee7696",
  "num": "lankadeepalk-49ee7696",
  "date_str": "2025-11-06",
  "description": "\u0db4\u0dcf\u0dc3\u0dbd\u0dca \u0d9a\u0dcf\u0dbd\u0dba \u0db4\u0dc3\u0dca\u0dc0\u0dbb\u0dd4 2 \u0daf\u0d9a\u0dca\u0dc0\u0dcf\u0db8 \u0dad\u0db8\u0dba\u0dd2",
  "url_metadata": "https://www.lankadeepa.lk/news/\u0db4\u0dc3\u0dbd-\u0d9a\u0dbd\u0dba-\u0db4\u0dc3\u0dc0\u0dbb-2-\u0daf\u0d9a\u0dc0\u0db8-\u0dad\u0db8\u0dba/101-682753",
  "lang": "si",
  "newspaper_id": "lankadeepalk",
  "time_ut": 1762439602.0
}