{
  "doc_type": "lk_news",
  "doc_id": "2025-11-29-lankadeepalk-6f093210",
  "num": "lankadeepalk-6f093210",
  "date_str": "2025-11-29",
  "description": "\u0dc4\u0dd0\u0da7\u0db1\u0dca \u0db4\u0dcf\u0dbb\u0dc0\u0dbd \u0db4\u0dc3\u0dca \u0d9a\u0db3\u0dd4 \u0d89\u0dc0\u0dad\u0dca\u0d9a\u0dbb\u0dba\u0dd2",
  "url_metadata": "https://www.lankadeepa.lk/news/\u0dc4\u0da7\u0db1-\u0db4\u0dbb\u0dc0\u0dbd-\u0db4\u0dc3-\u0d9a\u0db3-\u0d89\u0dc0\u0dad\u0d9a\u0dbb\u0dba/101-684251",
  "lang": "si",
  "newspaper_id": "lankadeepalk",
  "time_ut": 1764428563.0
}