{
  "doc_type": "lk_news",
  "doc_id": "2025-12-06-lankadeepalk-bf6b51ff",
  "num": "lankadeepalk-bf6b51ff",
  "date_str": "2025-12-06",
  "description": "\u0da2\u0db1\u0db4\u0dad\u0dd2 \u0db4\u0dcf\u0dbb\u0dca\u0dbd\u0dd2\u0db8\u0dda\u0db1\u0dca\u0dad\u0dd4\u0dc0 \u0d85\u0db8\u0dad\u0dcf \u0d9a\u0dc5 \u0dc3\u0db8\u0dca\u0db4\u0dd6\u0dbb\u0dca\u0dab \u0d9a\u0dad\u0dcf\u0dc0",
  "url_metadata": "https://www.lankadeepa.lk/latest_news/\u0da2\u0db1\u0db4\u0dad-\u0db4\u0dbb\u0dbd\u0db8\u0db1\u0dad\u0dc0-\u0d85\u0db8\u0dad-\u0d9a\u0dc5-\u0dc3\u0db8\u0db4\u0dbb\u0dab-\u0d9a\u0dad\u0dc0/1-684757",
  "lang": "si",
  "newspaper_id": "lankadeepalk",
  "time_ut": 1764990425.0
}