{
  "doc_type": "lk_news",
  "doc_id": "2025-01-08-adaderanasinhalalk-0385706d",
  "num": "adaderanasinhalalk-0385706d",
  "date_str": "2025-01-08",
  "description": "\u0db8\u0dcf\u0dc5\u0dd4 \u0db4\u0dcf\u0db1\u0dca \u0d9c\u0dd9\u0da9\u0dd2\u0dba\u0dd9\u0db1\u0dca \u0db8\u0dad\u0dd4 \u0dc0\u0dd6 \u0dbd\u0dba\u0dd2\u0da7\u0dbb\u0dca \u0d9a\u0dd1\u0dbd\u0dd2",
  "url_metadata": "http://sinhala.adaderana.lk/news/205181",
  "lang": "si",
  "newspaper_id": "adaderanasinhalalk",
  "time_ut": 1736339460.0
}