{
  "doc_type": "lk_news",
  "doc_id": "2024-02-21-dbsjeyarajcom-934117ca",
  "num": "dbsjeyarajcom-934117ca",
  "date_str": "2024-02-21",
  "description": "Construction of 1300 houses built under Phase-IV of Indian Housing Project (IHP) in 45 plantation estates across 10 Districts of Sri Lanka Virtually Launched on 19 Feb 2024 by President  Ranil Wickremesinghe and Indian Envoy Santosh Jha",
  "url_metadata": "https://dbsjeyaraj.com/dbsj/?p=83660",
  "lang": "en",
  "newspaper_id": "dbsjeyarajcom",
  "time_ut": 1708455960.0
}