{
  "doc_type": "lk_news",
  "doc_id": "2025-11-10-tamilmirrorlk-f9067fbc",
  "num": "tamilmirrorlk-f9067fbc",
  "date_str": "2025-11-10",
  "description": "10 \u0b86\u0ba3\u0bcd\u0b9f\u0bc1\u0b95\u0bb3\u0bc1\u0b95\u0bcd\u0b95\u0bc1\u0baa\u0bcd \u0baa\u0bbf\u0bb1\u0b95\u0bc1 \u0bb5\u0ba8\u0bcd\u0ba4 \u0ba8\u0bbe\u0bae\u0bb2\u0bcd",
  "url_metadata": "https://www.tamilmirror.lk/\u0b9a\u0bc6\u0baf\u0bcd\u0ba4\u0bbf\u0b95\u0bb3\u0bcd/10-\u0b86\u0ba3\u0bcd\u0b9f\u0bc1\u0b95\u0bb3\u0bc1\u0b95\u0bcd\u0b95\u0bc1\u0baa\u0bcd-\u0baa\u0bbf\u0bb1\u0b95\u0bc1-\u0bb5\u0ba8\u0bcd\u0ba4-\u0ba8\u0bbe\u0bae\u0bb2\u0bcd/175-367735",
  "lang": "ta",
  "newspaper_id": "tamilmirrorlk",
  "time_ut": 1762792239.0
}