{
  "doc_type": "lk_news",
  "doc_id": "2024-03-19-adaderanasinhalalk-3333a4d7",
  "num": "adaderanasinhalalk-3333a4d7",
  "date_str": "2024-03-19",
  "description": "\u0dc3\u0dd4\u0dbb\u0dad\u0dbd\u0dca \u0dc3\u0dad\u0dd4\u0db1\u0dca\u0d9c\u0dda \u0da2\u0dd3\u0dc0\u0dd2\u0dad\u0dba\u0da7 \u0d8b\u0dab\u0dd4\u0dc3\u0dd4\u0db8\u0dca \u0d9a\u0dcf\u0dbd\u0d9c\u0dd4\u0dab\u0dba\u0dd9\u0db1\u0dca \u0daf\u0dd0\u0da9\u0dd2 \u0db6\u0dbd\u0db4\u0dd1\u0db8\u0dca",
  "url_metadata": "http://sinhala.adaderana.lk/news/194677",
  "lang": "si",
  "newspaper_id": "adaderanasinhalalk",
  "time_ut": 1710834120.0
}